tqdm_thread/__init__.py
tqdm_thread-0.1.1.dist-info/LICENSE
tqdm_thread-0.1.1.dist-info/METADATA
tqdm_thread-0.1.1.dist-info/WHEEL
tqdm_thread-0.1.1.dist-info/top_level.txt
tqdm_thread-0.1.1.dist-info/RECORD
