Metadata-Version: 2.1
Name: tqdm-thread
Version: 0.1.1
Summary: TQDM context manager thread
Home-page: https://github.com/riklopfer/tqdm-thread
Author: Russell Klopfer
Author-email: russell.klopfer@gmail.com
License: MIT License
Platform: UNKNOWN
License-File: LICENSE
Requires-Dist: tqdm ; python_version >= "3.5"
